langmodels/VERSION
langmodels/__init__.py
langmodels/beamsearch.py
langmodels/cuda_util.py
langmodels/file_util.py
langmodels/logging.yaml
langmodels/migration.py
langmodels/model.py
langmodels/nn.py
langmodels/profiling.py
langmodels/tensor_ops.py
langmodels/util.py
langmodels/evaluation/__init__.py
langmodels/evaluation/customization.py
langmodels/evaluation/evaluation.py
langmodels/evaluation/metrics.py
langmodels/evaluation/normalization.py
langmodels/lmconfig/__init__.py
langmodels/lmconfig/datamodel.py
langmodels/lmconfig/patch.py
langmodels/lmconfig/serialization.py
langmodels/repository/__init__.py
langmodels/repository/convert.py
langmodels/repository/download.py
langmodels/repository/load.py
langmodels/repository/query.py
langmodels/repository/settings.py
langmodels/repository/upload.py
langmodels/training/__init__.py
langmodels/training/__main__.py
langmodels/training/cli.py
langmodels/training/data.py
langmodels/training/numericalize.py
langmodels/training/schedule.py
langmodels/training/subepoch_files.py
langmodels/training/tracking.py
langmodels/training/training.py
tests/__init__.py
tests/file_test_util.py
tests/test_beamsearch.py
tests/test_model.py
tests/config/__init__.py
tests/config/test_serialization.py
tests/evaluation/__init__.py
tests/evaluation/test_evaluation.py
tests/evaluation/test_metrics.py
tests/inference/__init__.py
tests/repository/__init__.py
tests/repository/test_convert.py
tests/training/__init__.py
tests/training/test_cli.py
tests/training/training.py
giganticode_langmodels-0.0.4a0.dist-info/LICENSE
giganticode_langmodels-0.0.4a0.dist-info/METADATA
giganticode_langmodels-0.0.4a0.dist-info/WHEEL
giganticode_langmodels-0.0.4a0.dist-info/top_level.txt
giganticode_langmodels-0.0.4a0.dist-info/RECORD
