Metadata-Version: 2.1
Name: giganticode-langmodels
Version: 0.0.4a0
Summary: A toolkit for applying machine learning to large source code corpora
Home-page: http://github.com/giganticode/langmodels
Author: giganticode
Author-email: hlibbabii@gmail.com
License: MIT
Keywords: big large data source code corpus machine learning nlp pytorch torch fastai language modeling
Platform: UNKNOWN
Classifier: Development Status :: 3 - Alpha
Classifier: Environment :: Console
Classifier: Intended Audience :: Science/Research
Classifier: License :: OSI Approved :: MIT License
Classifier: Natural Language :: English
Classifier: Programming Language :: Python :: 3.7
Classifier: Operating System :: POSIX :: Linux
Classifier: Operating System :: MacOS :: MacOS X
Classifier: Operating System :: Microsoft :: Windows
Classifier: Topic :: Scientific/Engineering :: Artificial Intelligence
Requires-Python: >=3.6
Requires-Dist: fastai (==1.0.57)
Requires-Dist: giganticode-dataprep (==1.0.0-alpha.12)
Requires-Dist: future (==0.18.2)
Requires-Dist: comet-ml (==3.0.2)
Requires-Dist: flatdict (==3.4.0)
Requires-Dist: retrying (==1.3.3)
Requires-Dist: psutil (==5.6.7)
Requires-Dist: tqdm (==4.39.0)
Requires-Dist: jsons (==1.0.0)
Requires-Dist: numpy (==1.17.4)
Requires-Dist: appdirs (==1.4.3)
Requires-Dist: Columnar (==1.3.1)
Requires-Dist: requests (==2.22.0)
Requires-Dist: pysftp (==0.2.9)
Requires-Dist: semver (==2.9.0)
Requires-Dist: jq (==0.1.6)
